{
  "gpus": [
    {
      "id": "rtx-5090",
      "name": "NVIDIA GeForce RTX 5090",
      "aliases": ["5090", "rtx5090", "rtx 5090", "geforce 5090"],
      "series": "RTX 50",
      "dlss5_support": "confirmed",
      "dlss5_features": ["neural_rendering"],
      "current_dlss_features": ["dlss_super_resolution", "dlaa", "ray_reconstruction", "multi_frame_generation_4x", "dynamic_mfg_6x"],
      "missing_features": [],
      "summary": "RTX 5090 is confirmed for DLSS 5 Neural Rendering (coming Fall 2026). Today it supports DLSS 4.5 with Dynamic 6X Multi Frame Generation and 2nd-gen Transformer Super Resolution.",
      "vram": "32GB",
      "tier": "flagship"
    },
    {
      "id": "rtx-5080",
      "name": "NVIDIA GeForce RTX 5080",
      "aliases": ["5080", "rtx5080", "rtx 5080", "geforce 5080"],
      "series": "RTX 50",
      "dlss5_support": "confirmed",
      "dlss5_features": ["neural_rendering"],
      "current_dlss_features": ["dlss_super_resolution", "dlaa", "ray_reconstruction", "multi_frame_generation_4x", "dynamic_mfg_6x"],
      "missing_features": [],
      "summary": "RTX 5080 is confirmed for DLSS 5 Neural Rendering (coming Fall 2026). Today it supports DLSS 4.5 with Dynamic 6X Multi Frame Generation.",
      "vram": "16GB",
      "tier": "high-end"
    },
    {
      "id": "rtx-5070-ti",
      "name": "NVIDIA GeForce RTX 5070 Ti",
      "aliases": ["5070ti", "5070 ti", "rtx5070ti", "rtx 5070 ti", "rtx5070 ti"],
      "series": "RTX 50",
      "dlss5_support": "confirmed",
      "dlss5_features": ["neural_rendering"],
      "current_dlss_features": ["dlss_super_resolution", "dlaa", "ray_reconstruction", "multi_frame_generation_4x", "dynamic_mfg_6x"],
      "missing_features": [],
      "summary": "RTX 5070 Ti is confirmed for DLSS 5 Neural Rendering (coming Fall 2026). Today it supports DLSS 4.5 with Dynamic 6X Multi Frame Generation.",
      "vram": "16GB",
      "tier": "high-end"
    },
    {
      "id": "rtx-5070",
      "name": "NVIDIA GeForce RTX 5070",
      "aliases": ["5070", "rtx5070", "rtx 5070", "geforce 5070"],
      "series": "RTX 50",
      "dlss5_support": "confirmed",
      "dlss5_features": ["neural_rendering"],
      "current_dlss_features": ["dlss_super_resolution", "dlaa", "ray_reconstruction", "multi_frame_generation_4x", "dynamic_mfg_6x"],
      "missing_features": [],
      "summary": "RTX 5070 is confirmed for DLSS 5 Neural Rendering (coming Fall 2026). Today it supports DLSS 4.5 with Dynamic 6X Multi Frame Generation.",
      "vram": "12GB",
      "tier": "mid-high"
    },
    {
      "id": "rtx-5060-ti",
      "name": "NVIDIA GeForce RTX 5060 Ti",
      "aliases": ["5060ti", "5060 ti", "rtx5060ti", "rtx 5060 ti"],
      "series": "RTX 50",
      "dlss5_support": "unlikely",
      "dlss5_features": [],
      "current_dlss_features": ["dlss_super_resolution", "dlaa", "ray_reconstruction", "multi_frame_generation_4x", "dynamic_mfg_6x"],
      "missing_features": ["neural_rendering"],
      "summary": "RTX 5060 Ti supports DLSS 4.5 Dynamic 6X MFG today. DLSS 5 Neural Rendering is unconfirmed — VRAM constraints may limit support. Status will be updated when NVIDIA publishes official specs.",
      "vram": "16GB",
      "tier": "mid"
    },
    {
      "id": "rtx-5060",
      "name": "NVIDIA GeForce RTX 5060",
      "aliases": ["5060", "rtx5060", "rtx 5060", "geforce 5060"],
      "series": "RTX 50",
      "dlss5_support": "unlikely",
      "dlss5_features": [],
      "current_dlss_features": ["dlss_super_resolution", "dlaa", "ray_reconstruction", "multi_frame_generation_4x", "dynamic_mfg_6x"],
      "missing_features": ["neural_rendering"],
      "summary": "RTX 5060 (8GB VRAM) supports DLSS 4.5 Dynamic 6X MFG today. DLSS 5 Neural Rendering is unlikely due to VRAM constraints — the GTC demo required a dedicated GPU with substantial memory.",
      "vram": "8GB",
      "tier": "mid"
    },
    {
      "id": "rtx-4090",
      "name": "NVIDIA GeForce RTX 4090",
      "aliases": ["4090", "rtx4090", "rtx 4090", "geforce 4090"],
      "series": "RTX 40",
      "dlss5_support": "possible",
      "dlss5_features": [],
      "current_dlss_features": ["dlss_super_resolution", "dlaa", "ray_reconstruction", "frame_generation"],
      "missing_features": ["neural_rendering"],
      "summary": "RTX 4090 DLSS 5 support is unconfirmed by NVIDIA. Partial support has been hinted but not guaranteed. Today it runs DLSS 4 with Frame Generation and Transformer Super Resolution.",
      "vram": "24GB",
      "tier": "flagship"
    },
    {
      "id": "rtx-4080-super",
      "name": "NVIDIA GeForce RTX 4080 Super",
      "aliases": ["4080s", "4080 super", "rtx4080super", "rtx 4080 super"],
      "series": "RTX 40",
      "dlss5_support": "possible",
      "dlss5_features": [],
      "current_dlss_features": ["dlss_super_resolution", "dlaa", "ray_reconstruction", "frame_generation"],
      "missing_features": ["neural_rendering"],
      "summary": "RTX 4080 Super DLSS 5 support is unconfirmed. Today it runs DLSS 4 with Frame Generation and Transformer Super Resolution.",
      "vram": "16GB",
      "tier": "high-end"
    },
    {
      "id": "rtx-4080",
      "name": "NVIDIA GeForce RTX 4080",
      "aliases": ["4080", "rtx4080", "rtx 4080", "geforce 4080"],
      "series": "RTX 40",
      "dlss5_support": "possible",
      "dlss5_features": [],
      "current_dlss_features": ["dlss_super_resolution", "dlaa", "ray_reconstruction", "frame_generation"],
      "missing_features": ["neural_rendering"],
      "summary": "RTX 4080 DLSS 5 support is unconfirmed. Today it runs DLSS 4 with Frame Generation and Transformer Super Resolution.",
      "vram": "16GB",
      "tier": "high-end"
    },
    {
      "id": "rtx-4070-ti-super",
      "name": "NVIDIA GeForce RTX 4070 Ti Super",
      "aliases": ["4070tis", "4070 ti super", "rtx 4070 ti super", "rtx4070tis"],
      "series": "RTX 40",
      "dlss5_support": "possible",
      "dlss5_features": [],
      "current_dlss_features": ["dlss_super_resolution", "dlaa", "ray_reconstruction", "frame_generation"],
      "missing_features": ["neural_rendering"],
      "summary": "RTX 4070 Ti Super DLSS 5 support is unconfirmed. Today it runs DLSS 4 with Frame Generation and Transformer Super Resolution.",
      "vram": "16GB",
      "tier": "high-end"
    },
    {
      "id": "rtx-4070-ti",
      "name": "NVIDIA GeForce RTX 4070 Ti",
      "aliases": ["4070ti", "4070 ti", "rtx4070ti", "rtx 4070 ti"],
      "series": "RTX 40",
      "dlss5_support": "possible",
      "dlss5_features": [],
      "current_dlss_features": ["dlss_super_resolution", "dlaa", "ray_reconstruction", "frame_generation"],
      "missing_features": ["neural_rendering"],
      "summary": "RTX 4070 Ti DLSS 5 support is unconfirmed. Today it runs DLSS 4 with Frame Generation.",
      "vram": "12GB",
      "tier": "mid-high"
    },
    {
      "id": "rtx-4070-super",
      "name": "NVIDIA GeForce RTX 4070 Super",
      "aliases": ["4070s", "4070 super", "rtx4070super", "rtx 4070 super"],
      "series": "RTX 40",
      "dlss5_support": "possible",
      "dlss5_features": [],
      "current_dlss_features": ["dlss_super_resolution", "dlaa", "ray_reconstruction", "frame_generation"],
      "missing_features": ["neural_rendering"],
      "summary": "RTX 4070 Super DLSS 5 support is unconfirmed. Today it runs DLSS 4 with Frame Generation.",
      "vram": "12GB",
      "tier": "mid"
    },
    {
      "id": "rtx-4070",
      "name": "NVIDIA GeForce RTX 4070",
      "aliases": ["4070", "rtx4070", "rtx 4070", "geforce 4070"],
      "series": "RTX 40",
      "dlss5_support": "possible",
      "dlss5_features": [],
      "current_dlss_features": ["dlss_super_resolution", "dlaa", "ray_reconstruction", "frame_generation"],
      "missing_features": ["neural_rendering"],
      "summary": "RTX 4070 DLSS 5 support is unconfirmed. Today it runs DLSS 4 with Frame Generation.",
      "vram": "12GB",
      "tier": "mid"
    },
    {
      "id": "rtx-4060-ti",
      "name": "NVIDIA GeForce RTX 4060 Ti",
      "aliases": ["4060ti", "4060 ti", "rtx4060ti", "rtx 4060 ti"],
      "series": "RTX 40",
      "dlss5_support": "possible",
      "dlss5_features": [],
      "current_dlss_features": ["dlss_super_resolution", "dlaa", "frame_generation"],
      "missing_features": ["neural_rendering"],
      "summary": "RTX 4060 Ti DLSS 5 support is unconfirmed. Today it runs DLSS 4 with Frame Generation.",
      "vram": "8GB",
      "tier": "mid"
    },
    {
      "id": "rtx-4060",
      "name": "NVIDIA GeForce RTX 4060",
      "aliases": ["4060", "rtx4060", "rtx 4060", "geforce 4060"],
      "series": "RTX 40",
      "dlss5_support": "possible",
      "dlss5_features": [],
      "current_dlss_features": ["dlss_super_resolution", "dlaa", "frame_generation"],
      "missing_features": ["neural_rendering"],
      "summary": "RTX 4060 DLSS 5 support is unconfirmed. Today it runs DLSS 4 with Frame Generation.",
      "vram": "8GB",
      "tier": "entry"
    },
    {
      "id": "rtx-3090-ti",
      "name": "NVIDIA GeForce RTX 3090 Ti",
      "aliases": ["3090ti", "3090 ti", "rtx3090ti", "rtx 3090 ti"],
      "series": "RTX 30",
      "dlss5_support": "unlikely",
      "dlss5_features": [],
      "current_dlss_features": ["dlss_super_resolution", "dlaa"],
      "missing_features": ["neural_rendering"],
      "summary": "RTX 3090 Ti is unlikely to support DLSS 5 Neural Rendering. Today it supports DLSS 4 Transformer-based Super Resolution and DLAA.",
      "vram": "24GB",
      "tier": "flagship"
    },
    {
      "id": "rtx-3090",
      "name": "NVIDIA GeForce RTX 3090",
      "aliases": ["3090", "rtx3090", "rtx 3090", "geforce 3090"],
      "series": "RTX 30",
      "dlss5_support": "unlikely",
      "dlss5_features": [],
      "current_dlss_features": ["dlss_super_resolution", "dlaa"],
      "missing_features": ["neural_rendering"],
      "summary": "RTX 3090 is unlikely to support DLSS 5 Neural Rendering. Today it supports DLSS 4 Transformer-based Super Resolution.",
      "vram": "24GB",
      "tier": "flagship"
    },
    {
      "id": "rtx-3080-ti",
      "name": "NVIDIA GeForce RTX 3080 Ti",
      "aliases": ["3080ti", "3080 ti", "rtx3080ti", "rtx 3080 ti"],
      "series": "RTX 30",
      "dlss5_support": "unlikely",
      "dlss5_features": [],
      "current_dlss_features": ["dlss_super_resolution", "dlaa"],
      "missing_features": ["neural_rendering"],
      "summary": "RTX 3080 Ti is unlikely to support DLSS 5. Today it supports DLSS 4 Transformer-based Super Resolution.",
      "vram": "12GB",
      "tier": "high-end"
    },
    {
      "id": "rtx-3080",
      "name": "NVIDIA GeForce RTX 3080",
      "aliases": ["3080", "rtx3080", "rtx 3080", "geforce 3080"],
      "series": "RTX 30",
      "dlss5_support": "unlikely",
      "dlss5_features": [],
      "current_dlss_features": ["dlss_super_resolution", "dlaa"],
      "missing_features": ["neural_rendering"],
      "summary": "RTX 3080 is unlikely to support DLSS 5. Today it supports DLSS 4 Transformer-based Super Resolution.",
      "vram": "10GB",
      "tier": "high-end"
    },
    {
      "id": "rtx-3070-ti",
      "name": "NVIDIA GeForce RTX 3070 Ti",
      "aliases": ["3070ti", "3070 ti", "rtx3070ti", "rtx 3070 ti"],
      "series": "RTX 30",
      "dlss5_support": "unlikely",
      "dlss5_features": [],
      "current_dlss_features": ["dlss_super_resolution", "dlaa"],
      "missing_features": ["neural_rendering"],
      "summary": "RTX 3070 Ti is unlikely to support DLSS 5. Today it supports DLSS 4 Transformer-based Super Resolution.",
      "vram": "8GB",
      "tier": "mid-high"
    },
    {
      "id": "rtx-3070",
      "name": "NVIDIA GeForce RTX 3070",
      "aliases": ["3070", "rtx3070", "rtx 3070", "geforce 3070"],
      "series": "RTX 30",
      "dlss5_support": "unlikely",
      "dlss5_features": [],
      "current_dlss_features": ["dlss_super_resolution", "dlaa"],
      "missing_features": ["neural_rendering"],
      "summary": "RTX 3070 is unlikely to support DLSS 5. Today it supports DLSS 4 Transformer-based Super Resolution.",
      "vram": "8GB",
      "tier": "mid"
    },
    {
      "id": "rtx-3060-ti",
      "name": "NVIDIA GeForce RTX 3060 Ti",
      "aliases": ["3060ti", "3060 ti", "rtx3060ti", "rtx 3060 ti"],
      "series": "RTX 30",
      "dlss5_support": "unlikely",
      "dlss5_features": [],
      "current_dlss_features": ["dlss_super_resolution", "dlaa"],
      "missing_features": ["neural_rendering"],
      "summary": "RTX 3060 Ti is unlikely to support DLSS 5. Today it supports DLSS 4 Transformer-based Super Resolution.",
      "vram": "8GB",
      "tier": "mid"
    },
    {
      "id": "rtx-3060",
      "name": "NVIDIA GeForce RTX 3060",
      "aliases": ["3060", "rtx3060", "rtx 3060", "geforce 3060"],
      "series": "RTX 30",
      "dlss5_support": "unlikely",
      "dlss5_features": [],
      "current_dlss_features": ["dlss_super_resolution", "dlaa"],
      "missing_features": ["neural_rendering"],
      "summary": "RTX 3060 is unlikely to support DLSS 5. Today it supports DLSS 4 Transformer-based Super Resolution.",
      "vram": "12GB",
      "tier": "mid"
    },
    {
      "id": "rtx-3050",
      "name": "NVIDIA GeForce RTX 3050",
      "aliases": ["3050", "rtx3050", "rtx 3050", "geforce 3050"],
      "series": "RTX 30",
      "dlss5_support": "unlikely",
      "dlss5_features": [],
      "current_dlss_features": ["dlss_super_resolution"],
      "missing_features": ["neural_rendering"],
      "summary": "RTX 3050 is unlikely to support DLSS 5. Today it supports basic DLSS Super Resolution.",
      "vram": "8GB",
      "tier": "entry"
    },
    {
      "id": "rtx-2080-ti",
      "name": "NVIDIA GeForce RTX 2080 Ti",
      "aliases": ["2080ti", "2080 ti", "rtx2080ti", "rtx 2080 ti"],
      "series": "RTX 20",
      "dlss5_support": "unlikely",
      "dlss5_features": [],
      "current_dlss_features": ["dlss_super_resolution"],
      "missing_features": ["neural_rendering"],
      "summary": "RTX 2080 Ti is unlikely to support DLSS 5. Today it supports DLSS 4 Transformer-based Super Resolution.",
      "vram": "11GB",
      "tier": "flagship"
    },
    {
      "id": "rtx-2080-super",
      "name": "NVIDIA GeForce RTX 2080 Super",
      "aliases": ["2080s", "2080 super", "rtx2080super", "rtx 2080 super"],
      "series": "RTX 20",
      "dlss5_support": "unlikely",
      "dlss5_features": [],
      "current_dlss_features": ["dlss_super_resolution"],
      "missing_features": ["neural_rendering"],
      "summary": "RTX 2080 Super is unlikely to support DLSS 5. Today it supports DLSS 4 Transformer-based Super Resolution.",
      "vram": "8GB",
      "tier": "high-end"
    },
    {
      "id": "rtx-2080",
      "name": "NVIDIA GeForce RTX 2080",
      "aliases": ["2080", "rtx2080", "rtx 2080", "geforce 2080"],
      "series": "RTX 20",
      "dlss5_support": "unlikely",
      "dlss5_features": [],
      "current_dlss_features": ["dlss_super_resolution"],
      "missing_features": ["neural_rendering"],
      "summary": "RTX 2080 is unlikely to support DLSS 5. Today it supports DLSS 4 Transformer-based Super Resolution.",
      "vram": "8GB",
      "tier": "high-end"
    },
    {
      "id": "rtx-2070-super",
      "name": "NVIDIA GeForce RTX 2070 Super",
      "aliases": ["2070s", "2070 super", "rtx2070super", "rtx 2070 super"],
      "series": "RTX 20",
      "dlss5_support": "unlikely",
      "dlss5_features": [],
      "current_dlss_features": ["dlss_super_resolution"],
      "missing_features": ["neural_rendering"],
      "summary": "RTX 2070 Super is unlikely to support DLSS 5. Today it supports DLSS 4 Transformer-based Super Resolution.",
      "vram": "8GB",
      "tier": "mid-high"
    },
    {
      "id": "rtx-2070",
      "name": "NVIDIA GeForce RTX 2070",
      "aliases": ["2070", "rtx2070", "rtx 2070", "geforce 2070"],
      "series": "RTX 20",
      "dlss5_support": "unlikely",
      "dlss5_features": [],
      "current_dlss_features": ["dlss_super_resolution"],
      "missing_features": ["neural_rendering"],
      "summary": "RTX 2070 is unlikely to support DLSS 5. Today it supports DLSS 4 Transformer-based Super Resolution.",
      "vram": "8GB",
      "tier": "mid"
    },
    {
      "id": "rtx-2060-super",
      "name": "NVIDIA GeForce RTX 2060 Super",
      "aliases": ["2060s", "2060 super", "rtx2060super", "rtx 2060 super"],
      "series": "RTX 20",
      "dlss5_support": "unlikely",
      "dlss5_features": [],
      "current_dlss_features": ["dlss_super_resolution"],
      "missing_features": ["neural_rendering"],
      "summary": "RTX 2060 Super is unlikely to support DLSS 5. Today it supports DLSS 4 Transformer-based Super Resolution.",
      "vram": "8GB",
      "tier": "mid"
    },
    {
      "id": "rtx-2060",
      "name": "NVIDIA GeForce RTX 2060",
      "aliases": ["2060", "rtx2060", "rtx 2060", "geforce 2060"],
      "series": "RTX 20",
      "dlss5_support": "unlikely",
      "dlss5_features": [],
      "current_dlss_features": ["dlss_super_resolution"],
      "missing_features": ["neural_rendering"],
      "summary": "RTX 2060 is unlikely to support DLSS 5. Today it supports DLSS 4 Transformer-based Super Resolution.",
      "vram": "6GB",
      "tier": "entry"
    },
    {
      "id": "gtx-1080-ti",
      "name": "NVIDIA GeForce GTX 1080 Ti",
      "aliases": ["1080ti", "1080 ti", "gtx1080ti", "gtx 1080 ti"],
      "series": "GTX 10",
      "dlss5_support": "none",
      "dlss5_features": [],
      "current_dlss_features": [],
      "missing_features": ["neural_rendering"],
      "summary": "GTX 1080 Ti does not support any version of DLSS. DLSS requires an NVIDIA RTX series GPU (RTX 20 or newer).",
      "vram": "11GB",
      "tier": "flagship"
    },
    {
      "id": "gtx-1080",
      "name": "NVIDIA GeForce GTX 1080",
      "aliases": ["1080", "gtx1080", "gtx 1080"],
      "series": "GTX 10",
      "dlss5_support": "none",
      "dlss5_features": [],
      "current_dlss_features": [],
      "missing_features": ["neural_rendering"],
      "summary": "GTX 1080 does not support any version of DLSS. DLSS requires an NVIDIA RTX series GPU.",
      "vram": "8GB",
      "tier": "high-end"
    },
    {
      "id": "gtx-1070-ti",
      "name": "NVIDIA GeForce GTX 1070 Ti",
      "aliases": ["1070ti", "1070 ti", "gtx1070ti", "gtx 1070 ti"],
      "series": "GTX 10",
      "dlss5_support": "none",
      "dlss5_features": [],
      "current_dlss_features": [],
      "missing_features": ["neural_rendering"],
      "summary": "GTX 1070 Ti does not support any version of DLSS. DLSS requires an NVIDIA RTX series GPU.",
      "vram": "8GB",
      "tier": "mid-high"
    },
    {
      "id": "gtx-1070",
      "name": "NVIDIA GeForce GTX 1070",
      "aliases": ["1070", "gtx1070", "gtx 1070"],
      "series": "GTX 10",
      "dlss5_support": "none",
      "dlss5_features": [],
      "current_dlss_features": [],
      "missing_features": ["neural_rendering"],
      "summary": "GTX 1070 does not support any version of DLSS. DLSS requires an NVIDIA RTX series GPU.",
      "vram": "8GB",
      "tier": "mid"
    },
    {
      "id": "gtx-1060",
      "name": "NVIDIA GeForce GTX 1060",
      "aliases": ["1060", "gtx1060", "gtx 1060"],
      "series": "GTX 10",
      "dlss5_support": "none",
      "dlss5_features": [],
      "current_dlss_features": [],
      "missing_features": ["neural_rendering"],
      "summary": "GTX 1060 does not support any version of DLSS. DLSS requires an NVIDIA RTX series GPU.",
      "vram": "6GB",
      "tier": "mid"
    },
    {
      "id": "amd-rx-7900-xtx",
      "name": "AMD Radeon RX 7900 XTX",
      "aliases": ["7900xtx", "7900 xtx", "rx7900xtx", "rx 7900 xtx", "radeon 7900 xtx"],
      "series": "AMD RX 7000",
      "dlss5_support": "none",
      "dlss5_features": [],
      "current_dlss_features": [],
      "missing_features": ["neural_rendering"],
      "summary": "AMD GPUs do not support DLSS (NVIDIA exclusive). However, FSR 4 (FidelityFX Super Resolution 4) is AMD's alternative upscaling technology.",
      "vram": "24GB",
      "tier": "flagship",
      "brand": "AMD"
    },
    {
      "id": "amd-rx-7800-xt",
      "name": "AMD Radeon RX 7800 XT",
      "aliases": ["7800xt", "7800 xt", "rx7800xt", "rx 7800 xt", "radeon 7800 xt"],
      "series": "AMD RX 7000",
      "dlss5_support": "none",
      "dlss5_features": [],
      "current_dlss_features": [],
      "missing_features": ["neural_rendering"],
      "summary": "AMD GPUs do not support DLSS (NVIDIA exclusive). FSR 4 is AMD's alternative upscaling technology.",
      "vram": "16GB",
      "tier": "mid-high",
      "brand": "AMD"
    },
    {
      "id": "amd-rx-7700-xt",
      "name": "AMD Radeon RX 7700 XT",
      "aliases": ["7700xt", "7700 xt", "rx7700xt", "rx 7700 xt"],
      "series": "AMD RX 7000",
      "dlss5_support": "none",
      "dlss5_features": [],
      "current_dlss_features": [],
      "missing_features": ["neural_rendering"],
      "summary": "AMD GPUs do not support DLSS (NVIDIA exclusive). FSR 4 is AMD's alternative upscaling technology.",
      "vram": "12GB",
      "tier": "mid",
      "brand": "AMD"
    },
    {
      "id": "intel-arc-b580",
      "name": "Intel Arc B580",
      "aliases": ["arc b580", "b580", "intel b580", "arc b580"],
      "series": "Intel Arc Battlemage",
      "dlss5_support": "none",
      "dlss5_features": [],
      "current_dlss_features": [],
      "missing_features": ["neural_rendering"],
      "summary": "Intel GPUs do not support DLSS (NVIDIA exclusive). Intel XeSS is Intel's alternative upscaling technology.",
      "vram": "12GB",
      "tier": "mid",
      "brand": "Intel"
    }
  ],
  "feature_descriptions": {
    "dlss_super_resolution": "DLSS Super Resolution -- 2nd-gen Transformer AI upscaling (DLSS 4/4.5)",
    "dlaa": "DLAA -- Deep Learning Anti-Aliasing for sharper image quality",
    "ray_reconstruction": "Ray Reconstruction -- AI-enhanced ray tracing quality (DLSS 3.5+)",
    "frame_generation": "Frame Generation -- Single AI-generated frame per rendered frame (DLSS 3, RTX 40)",
    "multi_frame_generation_4x": "Multi Frame Generation 4X -- 3 additional AI frames per rendered frame (DLSS 4, RTX 50)",
    "dynamic_mfg_6x": "Dynamic MFG 6X -- 5 additional AI frames per rendered frame (DLSS 4.5, RTX 50)",
    "neural_rendering": "Neural Rendering -- AI-powered photoreal lighting and materials (DLSS 5, coming Fall 2026)"
  }
}
